.gitignore
LICENSE.txt
MANIFEST.in
README.rst
pytest.ini
requirements.txt
setup.cfg
setup.py
.github/workflows/build.yml
bin/build_adjacency_graphs
bin/build_frequency_lists
data/english_wikipedia.txt
data/female_names.txt
data/male_names.txt
data/passwords.txt
data/surnames.txt
data/us_tv_and_film.txt
tests/__init__.py
tests/adjacency_graphs_test.py
tests/frequency_lists_test.py
tests/matching_test.py
tests/password_expected_value.json
tests/scoring_test.py
tests/test_compatibility.py
tests/time_estimates_test.py
tests/zxcvbn_test.py
zxcvbn/__init__.py
zxcvbn/__main__.py
zxcvbn/adjacency_graphs.py
zxcvbn/feedback.py
zxcvbn/frequency_lists.py
zxcvbn/matching.py
zxcvbn/scoring.py
zxcvbn/time_estimates.py
zxcvbn/types.py
zxcvbn_covert.egg-info/PKG-INFO
zxcvbn_covert.egg-info/SOURCES.txt
zxcvbn_covert.egg-info/dependency_links.txt
zxcvbn_covert.egg-info/entry_points.txt
zxcvbn_covert.egg-info/top_level.txt