Metadata-Version: 2.1
Name: zxcvbn-covert
Version: 5.0.1
Summary: UNKNOWN
Home-page: https://github.com/covert-encryption/zxcvbn-python/
Author: Daniel Wolf
Author-email: danielrwolf5@gmail.com
Maintainer: Covert Encryption
License: MIT
Keywords: zxcvbn,password,security
Platform: UNKNOWN
Classifier: Intended Audience :: Developers
Classifier: License :: OSI Approved :: MIT License
Classifier: Natural Language :: English
Classifier: Programming Language :: Python :: 3
Classifier: Programming Language :: Python :: 3.8
Classifier: Programming Language :: Python :: 3.9
Classifier: Programming Language :: Python :: 3.10
Classifier: Topic :: Security
Classifier: Topic :: Software Development :: Libraries :: Python Modules
License-File: LICENSE.txt
